campo_estatico_mdf/__init__.py
campo_estatico_mdf/solver.py
solver_campoelectrico_kevin-0.1.1.dist-info/METADATA
solver_campoelectrico_kevin-0.1.1.dist-info/WHEEL
solver_campoelectrico_kevin-0.1.1.dist-info/top_level.txt
solver_campoelectrico_kevin-0.1.1.dist-info/RECORD
