Metadata-Version: 2.4
Name: Solver_campoelectrico_kevin
Version: 0.1.1
Summary: Un solver para el campo electrostático 2D usando diferencias finitas.
Author-email: Estudiante Taller Avanzado <tu.email@example.com>
Project-URL: Homepage, https://github.com/tu_usuario/taller_electrostatica
Project-URL: Bug Tracker, https://github.com/tu_usuario/taller_electrostatica/issues
Classifier: Programming Language :: Python :: 3
Classifier: License :: OSI Approved :: MIT License
Classifier: Operating System :: OS Independent
Requires-Python: >=3.8
Requires-Dist: numpy>=1.20
Provides-Extra: dev
Requires-Dist: pytest; extra == "dev"
Requires-Dist: streamlit; extra == "dev"
Requires-Dist: matplotlib; extra == "dev"
Requires-Dist: sphinx; extra == "dev"
Requires-Dist: sphinx-rtd-theme; extra == "dev"
Requires-Dist: build; extra == "dev"
Requires-Dist: twine; extra == "dev"
